neuralhydrology/__about__.py
neuralhydrology/__init__.py
neuralhydrology/nh_run.py
neuralhydrology/nh_run_scheduler.py
neuralhydrology/datasetzoo/__init__.py
neuralhydrology/datasetzoo/basedataset.py
neuralhydrology/datasetzoo/camelsaus.py
neuralhydrology/datasetzoo/camelsbr.py
neuralhydrology/datasetzoo/camelscl.py
neuralhydrology/datasetzoo/camelsde.py
neuralhydrology/datasetzoo/camelsgb.py
neuralhydrology/datasetzoo/camelsind.py
neuralhydrology/datasetzoo/camelsus.py
neuralhydrology/datasetzoo/caravan.py
neuralhydrology/datasetzoo/datasetregistry.py
neuralhydrology/datasetzoo/genericdataset.py
neuralhydrology/datasetzoo/hourlycamelsus.py
neuralhydrology/datasetzoo/lamah.py
neuralhydrology/datasetzoo/template.py
neuralhydrology/datautils/__init__.py
neuralhydrology/datautils/climateindices.py
neuralhydrology/datautils/pet.py
neuralhydrology/datautils/utils.py
neuralhydrology/evaluation/__init__.py
neuralhydrology/evaluation/evaluate.py
neuralhydrology/evaluation/metrics.py
neuralhydrology/evaluation/plots.py
neuralhydrology/evaluation/signatures.py
neuralhydrology/evaluation/tester.py
neuralhydrology/evaluation/utils.py
neuralhydrology/modelzoo/__init__.py
neuralhydrology/modelzoo/arlstm.py
neuralhydrology/modelzoo/baseconceptualmodel.py
neuralhydrology/modelzoo/basemodel.py
neuralhydrology/modelzoo/cudalstm.py
neuralhydrology/modelzoo/customlstm.py
neuralhydrology/modelzoo/ealstm.py
neuralhydrology/modelzoo/embcudalstm.py
neuralhydrology/modelzoo/fc.py
neuralhydrology/modelzoo/gru.py
neuralhydrology/modelzoo/handoff_forecast_lstm.py
neuralhydrology/modelzoo/head.py
neuralhydrology/modelzoo/hybridmodel.py
neuralhydrology/modelzoo/inputlayer.py
neuralhydrology/modelzoo/mamba.py
neuralhydrology/modelzoo/mclstm.py
neuralhydrology/modelzoo/mtslstm.py
neuralhydrology/modelzoo/multihead_forecast_lstm.py
neuralhydrology/modelzoo/odelstm.py
neuralhydrology/modelzoo/positional_encoding.py
neuralhydrology/modelzoo/sequential_forecast_lstm.py
neuralhydrology/modelzoo/shm.py
neuralhydrology-1.13.0.dist-info/LICENSE
neuralhydrology-1.13.0.dist-info/METADATA
neuralhydrology-1.13.0.dist-info/WHEEL
neuralhydrology-1.13.0.dist-info/entry_points.txt
neuralhydrology-1.13.0.dist-info/top_level.txt
neuralhydrology-1.13.0.dist-info/RECORD
