Metadata-Version: 2.1
Name: neuralhydrology
Version: 1.13.0
Summary: Library for training deep learning models with environmental focus
Author-email: Frederik Kratzert <neuralhydrology@googlegroups.com>, Daniel Klotz <neuralhydrology@googlegroups.com>, Martin Gauch <neuralhydrology@googlegroups.com>
License: BSD-3-Clause
Project-URL: Documentation, https://neuralhydrology.readthedocs.io
Project-URL: Source, https://github.com/neuralhydrology/neuralhydrology
Project-URL: Research Blog, https://neuralhydrology.github.io/
Classifier: Programming Language :: Python :: 3
Classifier: Operating System :: OS Independent
Classifier: Topic :: Scientific/Engineering :: Artificial Intelligence
Classifier: Topic :: Scientific/Engineering :: Hydrology
Classifier: License :: OSI Approved :: BSD License
Requires-Python: >=3.10
License-File: LICENSE
Requires-Dist: matplotlib
Requires-Dist: numba
Requires-Dist: numpy
Requires-Dist: pandas
Requires-Dist: ruamel.yaml
Requires-Dist: torch
Requires-Dist: scipy
Requires-Dist: tensorboard
Requires-Dist: tqdm
Requires-Dist: xarray
Requires-Dist: netcdf4
Requires-Dist: h5py
